lonny_aws_blocks/__init__.py
lonny_aws_blocks/__main__.py
lonny_aws_blocks/base.py
lonny_aws_blocks/command.py
lonny_aws_blocks/dyno.py
lonny_aws_blocks/dyno_balancer.py
lonny_aws_blocks/dyno_config.py
lonny_aws_blocks/pipeline.py
lonny_aws_blocks/source.py
lonny_aws_blocks/type.py
lonny_aws_blocks-0.1.4.dist-info/WHEEL
lonny_aws_blocks-0.1.4.dist-info/METADATA
lonny_aws_blocks-0.1.4.dist-info/RECORD
